somadata/__init__.py
somadata/adat.py
somadata/annotations.py
somadata/base/__init__.py
somadata/base/adat_math_helpers.py
somadata/base/adat_meta_helpers.py
somadata/data/__init__.py
somadata/data/example_data.adat
somadata/data/example_data.py
somadata/data/lift.py
somadata/data/lift.zip
somadata/errors.py
somadata/io/__init__.py
somadata/io/adat/__init__.py
somadata/io/adat/errors.py
somadata/io/adat/file.py
somadata/io/annotations/__init__.py
somadata/io/annotations/errors.py
somadata/io/annotations/file.py
somadata/tools/__init__.py
somadata/tools/adat_concatenation.py
somadata/tools/adat_concatenation_utils.py
somadata/tools/errors.py
somadata/tools/math.py
somadata/tools/pandas.py
somadata-1.2.5.dist-info/METADATA
somadata-1.2.5.dist-info/WHEEL
somadata-1.2.5.dist-info/licenses/LICENSE
somadata-1.2.5.dist-info/RECORD
