Metadata-Version: 2.4
Name: somadata
Version: 1.2.5
Summary: SomaLogic Python Data Input/Output Library
License: MIT
License-File: LICENSE
Keywords: somalogic,bioinformatics,proteomics,canopy,adat
Author: SomaLogic
Author-email: support@somalogic.com
Requires-Python: >=3.9
Classifier: Programming Language :: Python :: 3
Classifier: Programming Language :: Python :: 3.9
Classifier: Programming Language :: Python :: 3.10
Classifier: Programming Language :: Python :: 3.11
Classifier: Programming Language :: Python :: 3.13
Classifier: Development Status :: 5 - Production/Stable
Classifier: Intended Audience :: Science/Research
Classifier: Operating System :: OS Independent
Classifier: Topic :: Scientific/Engineering
Requires-Dist: numpy (>=1.19)
Requires-Dist: openpyxl (>=3.0)
Requires-Dist: pandas (>=1.1.2)
Project-URL: Homepage, https://www.standardbio.com/
Project-URL: Repository, https://github.com/SomaLogic/Canopy
Project-URL: issues, https://github.com/SomaLogic/Canopy/issues
